{
  "columns": {
    "unassigned": { "issues": [], "order": 1 },
    "assigned": { "issues": ["4"], "order": 2 },
    "in progress": { "issues": ["3"], "order": 3 },
    "testing": { "issues": ["2"], "order": 4 },
    "completed": { "issues": ["1"], "order": 5 },
    "past": { "issues": ["5", "6"], "order": 6 }
  },
  "issues": [
    {
      "assignedTo": "Sasha",
      "body": "This is the body of the first issue.",
      "id": "1",
      "title": "Issues Number One"
    },
    {
      "assignedTo": "Franklin",
      "body": "This is the body of the second issue.",
      "id": "2",
      "title": "Issues Number Two"
    },
    {
      "assignedTo": "Michael",
      "body": "This is the body of the third issue.",
      "id": "3",
      "title": "Issues Number Three"
    },
    {
      "assignedTo": null,
      "body": "This is the body of the fourth issue.",
      "id": "4",
      "title": "Issues Number Four"
    },
    {
      "assignedTo": "Billy",
      "body": "This is the body of the fifth issue.",
      "id": "5",
      "title": "Issues Number Five"
    },
    {
      "assignedTo": "Trevor",
      "body": "This is the body of the sixth issue.",
      "id": "6",
      "title": "Issues Number Six"
    }
  ],
  "users": ["Sasha", "Franklin", "Michael", "Trevor"]
}
